{
  "last_updated": "2026-07-10T16:48:40.245625+00:00",
  "overall": {
    "total_trades": 30,
    "open_trades": 1,
    "closed_trades": 29,
    "winners": 10,
    "losers": 19,
    "win_rate": 34.5,
    "total_pnl": -40.08,
    "best_trade": 30.0,
    "worst_trade": -11.65,
    "average_win": 11.57,
    "average_loss": -8.2,
    "expectancy": -1.38,
    "max_drawdown": -62.97,
    "current_streak": -9
  },
  "by_epic": {
    "GOLD": {
      "trades": 7,
      "winners": 2,
      "losers": 5,
      "win_rate": 28.6,
      "pnl": -11.86
    },
    "SILVER": {
      "trades": 13,
      "winners": 4,
      "losers": 9,
      "win_rate": 30.8,
      "pnl": -22.56
    },
    "COPPER": {
      "trades": 9,
      "winners": 4,
      "losers": 5,
      "win_rate": 44.4,
      "pnl": -5.66
    }
  }
}